sep005_io_fbgs/__init__.py
sep005_io_fbgs/fbgs.py
sep005_io_fbgs-0.0.2.dist-info/METADATA
sep005_io_fbgs-0.0.2.dist-info/WHEEL
sep005_io_fbgs-0.0.2.dist-info/top_level.txt
sep005_io_fbgs-0.0.2.dist-info/RECORD
